{
  "formatVersion": 1,
  "database": {
    "version": 1,
    "identityHash": "616d3a9562569105076d2883bbe92f7c",
    "entities": [
      {
        "tableName": "Contato",
        "createSql": "CREATE TABLE IF NOT EXISTS `${TABLE_NAME}` (`id` INTEGER PRIMARY KEY AUTOINCREMENT NOT NULL, `nome` TEXT NOT NULL, `sobrenome` TEXT NOT NULL, `telefone` TEXT NOT NULL, `fotoPerfil` TEXT NOT NULL, `aniversario` INTEGER)",
        "fields": [
          {
            "fieldPath": "id",
            "columnName": "id",
            "affinity": "INTEGER",
            "notNull": true
          },
          {
            "fieldPath": "nome",
            "columnName": "nome",
            "affinity": "TEXT",
            "notNull": true
          },
          {
            "fieldPath": "sobrenome",
            "columnName": "sobrenome",
            "affinity": "TEXT",
            "notNull": true
          },
          {
            "fieldPath": "telefone",
            "columnName": "telefone",
            "affinity": "TEXT",
            "notNull": true
          },
          {
            "fieldPath": "fotoPerfil",
            "columnName": "fotoPerfil",
            "affinity": "TEXT",
            "notNull": true
          },
          {
            "fieldPath": "aniversario",
            "columnName": "aniversario",
            "affinity": "INTEGER",
            "notNull": false
          }
        ],
        "primaryKey": {
          "autoGenerate": true,
          "columnNames": [
            "id"
          ]
        },
        "indices": [],
        "foreignKeys": []
      }
    ],
    "views": [],
    "setupQueries": [
      "CREATE TABLE IF NOT EXISTS room_master_table (id INTEGER PRIMARY KEY,identity_hash TEXT)",
      "INSERT OR REPLACE INTO room_master_table (id,identity_hash) VALUES(42, '616d3a9562569105076d2883bbe92f7c')"
    ]
  }
}